sbo_service_purchasing/__init__.py
sbo_service_purchasing/purchasing.py
sbo_service_purchasing-0.1.2.dist-info/METADATA
sbo_service_purchasing-0.1.2.dist-info/WHEEL
sbo_service_purchasing-0.1.2.dist-info/top_level.txt
sbo_service_purchasing-0.1.2.dist-info/RECORD
