Metadata-Version: 2.1
Name: sbo_service_purchasing
Version: 0.1.2
Home-page: https://bitbucket.org/jaydm/sbo-service-purchasing
Author: Jay D. McHugh
Author-email: 'Jay D. McHugh' <jaydmchugh@gmail.com>
License: Apache-2.0
Classifier: License :: OSI Approved :: Apache Software License
Requires-Python: >=3.9
Requires-Dist: requests <3,>=2.28
Requires-Dist: urllib3 <2,>=1.26
Requires-Dist: python-dotenv <2,>=1
Requires-Dist: sbo-service-layer <1,>=0.1.1
Requires-Dist: sbo-service-inventory <1,>=0.1.1
